TkThemes/__init__.py
TkThemes/themes.py
tkthemes-0.1.2.dist-info/licenses/LICENSE
tkthemes-0.1.2.dist-info/METADATA
tkthemes-0.1.2.dist-info/WHEEL
tkthemes-0.1.2.dist-info/top_level.txt
tkthemes-0.1.2.dist-info/RECORD
