Metadata-Version: 2.4
Name: TkThemes
Version: 0.1.2
Summary: Contains dictionary of custom themes used for creting GUIs with Tkinter
Home-page: https://github.com/TirthrajSG/TkThemes
Author: Tirthraj Girawale
Requires-Python: >=3.7
License-File: LICENSE
Dynamic: author
Dynamic: description
Dynamic: description-content-type
Dynamic: home-page
Dynamic: license-file
Dynamic: requires-python
Dynamic: summary
